AstroSynthWrappers/__init__.py
AstroSynthWrappers/PTF/__init__.py
AstroSynthWrappers/PTF/ptf.py
AstroSynthWrappers/PTF/transfer2db.py
AstroSynthWrappers/PTF/utils/__init__.py
AstroSynthWrappers/PTF/utils/resample.py
AstroSynthWrappers-0.1.21.dist-info/DESCRIPTION.rst
AstroSynthWrappers-0.1.21.dist-info/METADATA
AstroSynthWrappers-0.1.21.dist-info/RECORD
AstroSynthWrappers-0.1.21.dist-info/WHEEL
AstroSynthWrappers-0.1.21.dist-info/metadata.json
AstroSynthWrappers-0.1.21.dist-info/top_level.txt
