Metadata-Version: 2.0
Name: AstroSynthWrappers
Version: 0.1.21
Summary: Data Wrappers meant to mimic the astroSynth data interface
Home-page: https://github.com/tboudreaux/AstroSynthWrappers.git
Author: Thomas Boudreaux
Author-email: thomas@boudreauxmail.com
License: MIT
Platform: UNKNOWN
Classifier: Development Status :: 3 - Alpha
Classifier: Intended Audience :: Science/Research
Classifier: License :: OSI Approved :: MIT License
Classifier: Programming Language :: Python :: 3
Requires-Dist: astropy (>=2.0.2)
Requires-Dist: numpy (>=1.14.1)
Requires-Dist: pandas (>=0.20.3)
Requires-Dist: pymongo (>=3.5.1)
Requires-Dist: scipy (>=1.0.0)
Requires-Dist: tqdm (>=4.19.4)
